{
    "process_path": "CONFIGS_COST_SPD3/slo_1000/cv_0.1/mean_provision/lambda_552/552_0.1.deltas", 
    "batch_size": 62, 
    "gpu_affinities": [
        "0 1 2"
    ], 
    "num_trials": 30, 
    "cpu_affinities": [
        "0 1 2 16 17 18"
    ], 
    "trial_length": 2760, 
    "replica_nums": [
        3
    ], 
    "slo_millis": 1000, 
    "cv": 0.1, 
    "process_mean_thru": 551.1594550253159, 
    "max_estimated_thru": 611.3112873297391, 
    "process_peak_thru": 571.0, 
    "lambda": 552
}